taskwarrior_capsules/__init__.py
taskwarrior_capsules/capsule.py
taskwarrior_capsules/capsule_meta.py
taskwarrior_capsules/cmdline.py
taskwarrior_capsules/data.py
taskwarrior_capsules/exceptions.py
taskwarrior_capsules/commands/__init__.py
taskwarrior_capsules/commands/main.py
taskwarrior_capsules-1.0.1.dist-info/LICENSE
taskwarrior_capsules-1.0.1.dist-info/METADATA
taskwarrior_capsules-1.0.1.dist-info/WHEEL
taskwarrior_capsules-1.0.1.dist-info/entry_points.txt
taskwarrior_capsules-1.0.1.dist-info/top_level.txt
taskwarrior_capsules-1.0.1.dist-info/RECORD
