Metadata-Version: 2.1
Name: taskwarrior-capsules
Version: 1.0.1
Summary: Extend Taskwarrior via capsules (plugins).
Home-page: https://github.com/coddingtonbear/taskwarrior-capsules
Author: Adam Coddington
Author-email: me@adamcoddington.net
License: UNKNOWN
Platform: UNKNOWN
Classifier: License :: OSI Approved :: MIT License
Classifier: Operating System :: OS Independent
Classifier: Programming Language :: Python :: 3
Requires-Dist: configobj (<5.1,>=5.0.6)
Requires-Dist: blessings (<1.6.0,>=1.5.1)
Requires-Dist: verlib (<1.0,>=0.1)
Requires-Dist: taskw (<2.0,>=1.0.3)
Requires-Dist: pytz
